{
  "updatedAt": "2026-07-15T00:00:54.217Z",
  "pairs": {
    "XAUUSD": {
      "swing": {
        "signal": "HOLD",
        "suppressionReason": "NO TRADE — stopped at \"MACD Confirmation\"",
        "tradePlan": null,
        "passCount": 2,
        "gatedCount": 3
      },
      "intraday": {
        "signal": "HOLD",
        "suppressionReason": "NO TRADE — no confirmed trend direction yet",
        "tradePlan": null,
        "passCount": 0,
        "gatedCount": 1
      },
      "scalp": {
        "decision": "BUY",
        "reason": "",
        "perTF": [
          {
            "tf": "5m",
            "signal": "BUY"
          },
          {
            "tf": "15m",
            "signal": "BUY"
          },
          {
            "tf": "30m",
            "signal": "BUY"
          }
        ],
        "entry": 4054.11,
        "sl": 4050.85,
        "tp": 4060.65,
        "rr": 2
      },
      "master": {
        "verdict": "MIXED",
        "votes": [
          {
            "engine": "Scalp",
            "signal": "BUY"
          },
          {
            "engine": "Intraday",
            "signal": "HOLD"
          },
          {
            "engine": "Swing",
            "signal": "HOLD"
          }
        ]
      }
    },
    "GBPJPY": {
      "swing": {
        "signal": "HOLD",
        "suppressionReason": "NO TRADE — stopped at \"Candle Pattern\"",
        "tradePlan": null,
        "passCount": 5,
        "gatedCount": 6
      },
      "intraday": {
        "signal": "HOLD",
        "suppressionReason": "NO TRADE — stopped at \"Candle Pattern\"",
        "tradePlan": null,
        "passCount": 5,
        "gatedCount": 6
      },
      "scalp": {
        "decision": "BUY",
        "reason": "",
        "perTF": [
          {
            "tf": "5m",
            "signal": "BUY"
          },
          {
            "tf": "15m",
            "signal": "BUY"
          },
          {
            "tf": "30m",
            "signal": "BUY"
          }
        ],
        "entry": 217.278,
        "sl": 217.199,
        "tp": 217.434,
        "rr": 2
      },
      "master": {
        "verdict": "MIXED",
        "votes": [
          {
            "engine": "Scalp",
            "signal": "BUY"
          },
          {
            "engine": "Intraday",
            "signal": "HOLD"
          },
          {
            "engine": "Swing",
            "signal": "HOLD"
          }
        ]
      }
    }
  }
}